voice100/__init__.py
voice100/align_text.py
voice100/audio.py
voice100/cache_dataset.py
voice100/calc_stat.py
voice100/data_modules.py
voice100/export_onnx.py
voice100/export_onnx_v1.py
voice100/japanese/__init__.py
voice100/japanese/phonemizer.py
voice100/main.py
voice100/models/__init__.py
voice100/models/_align_v2.py
voice100/models/_asr_v2.py
voice100/models/_base.py
voice100/models/_layers_v1.py
voice100/models/_layers_v2.py
voice100/models/_tts_v2.py
voice100/models/align.py
voice100/models/asr.py
voice100/models/tts.py
voice100/prepare_dataset.py
voice100/text.py
voice100/train_align.py
voice100/train_asr.py
voice100/train_ttsalign.py
voice100/train_ttsaudio.py
voice100/train_ttsaudio_mt.py
voice100/update_samples.py
voice100/vocoder.py
voice100-1.6.0.dist-info/LICENSE
voice100-1.6.0.dist-info/METADATA
voice100-1.6.0.dist-info/WHEEL
voice100-1.6.0.dist-info/entry_points.txt
voice100-1.6.0.dist-info/RECORD
