Metadata-Version: 2.1
Name: voice100
Version: 1.6.0
Summary: Voice100 is a small TTS for English and Japanese.
License: MIT
Author: Katsuya Iida
Author-email: katsuya.iida@gmail.com
Requires-Python: >=3.8.1,<4.0.0
Classifier: License :: OSI Approved :: MIT License
Classifier: Programming Language :: Python :: 3
Classifier: Programming Language :: Python :: 3.9
Classifier: Programming Language :: Python :: 3.10
Classifier: Programming Language :: Python :: 3.11
Provides-Extra: lang-en-phone
Provides-Extra: lang-ja
Provides-Extra: tts
Requires-Dist: fugashi (>=1.2.1,<2.0.0) ; extra == "lang-ja"
Requires-Dist: g2p-en (>=2.1.0,<3.0.0) ; extra == "lang-en-phone"
Requires-Dist: pytorch_lightning[extra] (>=1.5,<2.0)
Requires-Dist: pyworld (>=0.3.2,<0.4.0) ; extra == "tts"
Requires-Dist: torch (>=1.12,<2.0)
Requires-Dist: torchaudio (>=0,<1)
Requires-Dist: unidic-lite (>=1.0.8,<2.0.0) ; extra == "lang-ja"
